.travis.yml
LICENSE
MANIFEST.in
README.rst
setup.cfg
setup.py
Mopidy_PlaybackDefaults.egg-info/PKG-INFO
Mopidy_PlaybackDefaults.egg-info/SOURCES.txt
Mopidy_PlaybackDefaults.egg-info/dependency_links.txt
Mopidy_PlaybackDefaults.egg-info/entry_points.txt
Mopidy_PlaybackDefaults.egg-info/not-zip-safe
Mopidy_PlaybackDefaults.egg-info/requires.txt
Mopidy_PlaybackDefaults.egg-info/top_level.txt
mopidy_playbackdefaults/__init__.py
mopidy_playbackdefaults/ext.conf
tests/__init__.py
tests/test_extension.py
tests/test_frontend.py