Metadata-Version: 1.2
Name: Mopidy-PlaybackDefaults
Version: 0.1.2
Summary: Mopidy extension for configurable default playback settings.
Home-page: https://github.com/DavisNT/mopidy-playbackdefaults
Author: Davis Mosenkovs
Author-email: python-apps@dm.id.lv
License: Apache License, Version 2.0
Platform: UNKNOWN
Classifier: Environment :: No Input/Output (Daemon)
Classifier: Intended Audience :: End Users/Desktop
Classifier: License :: OSI Approved :: Apache Software License
Classifier: Operating System :: OS Independent
Classifier: Programming Language :: Python :: 3
Classifier: Topic :: Multimedia :: Sound/Audio :: Players
Requires-Python: >= 3.7
